frontman/__init__.py
frontman/__main__.py
frontman/download.py
frontman/main.py
frontman/process.py
frontman/provider.py
frontman/result.py
frontman/schema.py
frontman-0.3.1.dist-info/entry_points.txt
frontman-0.3.1.dist-info/WHEEL
frontman-0.3.1.dist-info/METADATA
frontman-0.3.1.dist-info/RECORD
