Metadata-Version: 2.1
Name: frontman
Version: 0.3.1
Summary: Frontend Library Manager
Home-page: https://github.com/livioribeiro/frontman
License: MIT
Author: Livio Ribeiro
Author-email: livioribeiro@outlook.com
Requires-Python: >=3.7,<4.0
Classifier: License :: OSI Approved :: MIT License
Classifier: Programming Language :: Python :: 3
Classifier: Programming Language :: Python :: 3.10
Classifier: Programming Language :: Python :: 3.7
Classifier: Programming Language :: Python :: 3.8
Classifier: Programming Language :: Python :: 3.9
Requires-Dist: pydantic (>=1.9.1,<2.0.0)
Requires-Dist: requests (>=2.28.1,<3.0.0)
Requires-Dist: typer[all] (>=0.5.0,<0.6.0)
Project-URL: Repository, https://github.com/livioribeiro/frontman
